verilog/cla_tb.v
`timescale 1ns/1ps

module and2(input a, input b, output y);
    assign y = a & b;
endmodule

module and3(input a, input b, input c, output y);
    assign y = a & b & c;
endmodule

module and4(input a, input b, input c, input d, output y);
    assign y = a & b & c & d;
endmodule

module and5(input a, input b, input c, input d, input e, output y);
    assign y = a & b & c & d & e;
endmodule

module and6(input a, input b, input c, input d, input e, input f, output y);
    assign y = a & b & c & d & e & f;
endmodule

module or2(input a, input b, output y);
    assign y = a | b;
endmodule

module or3(input a, input b, input c, output y);
    assign y = a | b | c;
endmodule

module or4(input a, input b, input c, input d, output y);
    assign y = a | b | c | d;
endmodule

module or5(input a, input b, input c, input d, input e, output y);
    assign y = a | b | c | d | e;
endmodule

module or6(input a, input b, input c, input d, input e, input f, output y);
    assign y = a | b | c | d | e | f;
endmodule

module xor2(input a, input b, output y);
    assign y = a ^ b;
endmodule

module carry_lookahead_adder_5bit_modular(
    input  [4:0] A,
    input  [4:0] B,
    input  Cin,
    output [4:0] Sum,
    output Cout
);

    wire [4:0] G, P;
    wire C1, C2, C3, C4;

    and2 g0(A[0], B[0], G[0]);
    and2 g1(A[1], B[1], G[1]);
    and2 g2(A[2], B[2], G[2]);
    and2 g3(A[3], B[3], G[3]);
    and2 g4(A[4], B[4], G[4]);

    xor2 p0(A[0], B[0], P[0]);
    xor2 p1(A[1], B[1], P[1]);
    xor2 p2(A[2], B[2], P[2]);
    xor2 p3(A[3], B[3], P[3]);
    xor2 p4(A[4], B[4], P[4]);

    wire term_c1, term1_c2, term2_c2;
    wire term1_c3, term2_c3, term3_c3;
    wire term1_c4, term2_c4, term3_c4, term4_c4;
    wire term1_cout, term2_cout, term3_cout, term4_cout, term5_cout;

    and2 and_c1(P[0], Cin, term_c1);
    or2  or_c1(G[0], term_c1, C1);

    and2 and1_c2(P[1], G[0], term1_c2);
    and3 and2_c2(P[1], P[0], Cin, term2_c2);
    or3  or_c2(G[1], term1_c2, term2_c2, C2);

    and2 and1_c3(P[2], G[1], term1_c3);
    and3 and2_c3(P[2], P[1], G[0], term2_c3);
    and4 and3_c3(P[2], P[1], P[0], Cin, term3_c3);
    or4  or_c3(G[2], term1_c3, term2_c3, term3_c3, C3);

    and2 and1_c4(P[3], G[2], term1_c4);
    and3 and2_c4(P[3], P[2], G[1], term2_c4);
    and4 and3_c4(P[3], P[2], P[1], G[0], term3_c4);
    and5 and4_c4(P[3], P[2], P[1], P[0], Cin, term4_c4);
    or5  or_c4(G[3], term1_c4, term2_c4, term3_c4, term4_c4, C4);

    and2 and1_cout(P[4], G[3], term1_cout);
    and3 and2_cout(P[4], P[3], G[2], term2_cout);
    and4 and3_cout(P[4], P[3], P[2], G[1], term3_cout);
    and5 and4_cout(P[4], P[3], P[2], P[1], G[0], term4_cout);
    and6 and5_cout(P[4], P[3], P[2], P[1], P[0], Cin, term5_cout);
    or6  or_cout(G[4], term1_cout, term2_cout, term3_cout, term4_cout, term5_cout, Cout);

    xor2 sum0(P[0], Cin, Sum[0]);
    xor2 sum1(P[1], C1,  Sum[1]);
    xor2 sum2(P[2], C2,  Sum[2]);
    xor2 sum3(P[3], C3,  Sum[3]);
    xor2 sum4(P[4], C4,  Sum[4]);

endmodule

module tb_carry_lookahead_adder_5bit_modular;

    reg  [4:0] A;
    reg  [4:0] B;
    reg  Cin;
    wire [4:0] Sum;
    wire Cout;

    carry_lookahead_adder_5bit_modular uut(
        .A(A), .B(B), .Cin(Cin),
        .Sum(Sum), .Cout(Cout)
    );

    reg clk = 0;
    always #5 clk = ~clk;

    initial begin
        $dumpfile("waveforms.vcd");
        $dumpvars(0, tb_carry_lookahead_adder_5bit_modular);
    end

    initial begin
        $display(" time | Cin |   A   |   B   |  Sum  | Cout");
        $monitor("%5t |  %b  | %02d  | %02d  |  %02d   |  %b",
                  $time, Cin, A, B, Sum, Cout);
    end

    initial begin
        Cin = 0;
        A = 5'b00000; B = 5'b00001; repeat(4) @(posedge clk);
        A = 5'b00010; B = 5'b00011; repeat(4) @(posedge clk);
        A = 5'b00100; B = 5'b00101; repeat(4) @(posedge clk);
        A = 5'b01000; B = 5'b01001; repeat(4) @(posedge clk);
        A = 5'b10000; B = 5'b10001; repeat(4) @(posedge clk);

        Cin = 1;
        A = 5'b10101; B = 5'b01110; repeat(4) @(posedge clk);

        Cin = 0;
        A = 5'b11100; B = 5'b00011; repeat(4) @(posedge clk);

        Cin = 1;
        A = 5'b00111; B = 5'b11000; repeat(4) @(posedge clk);

        $finish;
    end

endmodule

verilog/waveforms.vcd
$date
	Wed Dec  3 19:48:35 2025
$end
$version
	Icarus Verilog
$end
$timescale
	1ps
$end
$scope module tb_carry_lookahead_adder_5bit_modular $end
$var wire 5 ! Sum [4:0] $end
$var wire 1 " Cout $end
$var reg 5 # A [4:0] $end
$var reg 5 $ B [4:0] $end
$var reg 1 % Cin $end
$var reg 1 & clk $end
$scope module uut $end
$var wire 5 ' A [4:0] $end
$var wire 5 ( B [4:0] $end
$var wire 1 % Cin $end
$var wire 1 ) term_c1 $end
$var wire 1 * term5_cout $end
$var wire 1 + term4_cout $end
$var wire 1 , term4_c4 $end
$var wire 1 - term3_cout $end
$var wire 1 . term3_c4 $end
$var wire 1 / term3_c3 $end
$var wire 1 0 term2_cout $end
$var wire 1 1 term2_c4 $end
$var wire 1 2 term2_c3 $end
$var wire 1 3 term2_c2 $end
$var wire 1 4 term1_cout $end
$var wire 1 5 term1_c4 $end
$var wire 1 6 term1_c3 $end
$var wire 1 7 term1_c2 $end
$var wire 5 8 Sum [4:0] $end
$var wire 5 9 P [4:0] $end
$var wire 5 : G [4:0] $end
$var wire 1 " Cout $end
$var wire 1 ; C4 $end
$var wire 1 < C3 $end
$var wire 1 = C2 $end
$var wire 1 > C1 $end
$scope module and1_c2 $end
$var wire 1 ? a $end
$var wire 1 @ b $end
$var wire 1 7 y $end
$upscope $end
$scope module and1_c3 $end
$var wire 1 A a $end
$var wire 1 B b $end
$var wire 1 6 y $end
$upscope $end
$scope module and1_c4 $end
$var wire 1 C a $end
$var wire 1 D b $end
$var wire 1 5 y $end
$upscope $end
$scope module and1_cout $end
$var wire 1 E a $end
$var wire 1 F b $end
$var wire 1 4 y $end
$upscope $end
$scope module and2_c2 $end
$var wire 1 G a $end
$var wire 1 H b $end
$var wire 1 % c $end
$var wire 1 3 y $end
$upscope $end
$scope module and2_c3 $end
$var wire 1 I a $end
$var wire 1 J b $end
$var wire 1 K c $end
$var wire 1 2 y $end
$upscope $end
$scope module and2_c4 $end
$var wire 1 L a $end
$var wire 1 M b $end
$var wire 1 N c $end
$var wire 1 1 y $end
$upscope $end
$scope module and2_cout $end
$var wire 1 O a $end
$var wire 1 P b $end
$var wire 1 Q c $end
$var wire 1 0 y $end
$upscope $end
$scope module and3_c3 $end
$var wire 1 R a $end
$var wire 1 S b $end
$var wire 1 T c $end
$var wire 1 % d $end
$var wire 1 / y $end
$upscope $end
$scope module and3_c4 $end
$var wire 1 U a $end
$var wire 1 V b $end
$var wire 1 W c $end
$var wire 1 X d $end
$var wire 1 . y $end
$upscope $end
$scope module and3_cout $end
$var wire 1 Y a $end
$var wire 1 Z b $end
$var wire 1 [ c $end
$var wire 1 \ d $end
$var wire 1 - y $end
$upscope $end
$scope module and4_c4 $end
$var wire 1 ] a $end
$var wire 1 ^ b $end
$var wire 1 _ c $end
$var wire 1 ` d $end
$var wire 1 % e $end
$var wire 1 , y $end
$upscope $end
$scope module and4_cout $end
$var wire 1 a a $end
$var wire 1 b b $end
$var wire 1 c c $end
$var wire 1 d d $end
$var wire 1 e e $end
$var wire 1 + y $end
$upscope $end
$scope module and5_cout $end
$var wire 1 f a $end
$var wire 1 g b $end
$var wire 1 h c $end
$var wire 1 i d $end
$var wire 1 j e $end
$var wire 1 % f $end
$var wire 1 * y $end
$upscope $end
$scope module and_c1 $end
$var wire 1 k a $end
$var wire 1 % b $end
$var wire 1 ) y $end
$upscope $end
$scope module g0 $end
$var wire 1 l a $end
$var wire 1 m b $end
$var wire 1 n y $end
$upscope $end
$scope module g1 $end
$var wire 1 o a $end
$var wire 1 p b $end
$var wire 1 q y $end
$upscope $end
$scope module g2 $end
$var wire 1 r a $end
$var wire 1 s b $end
$var wire 1 t y $end
$upscope $end
$scope module g3 $end
$var wire 1 u a $end
$var wire 1 v b $end
$var wire 1 w y $end
$upscope $end
$scope module g4 $end
$var wire 1 x a $end
$var wire 1 y b $end
$var wire 1 z y $end
$upscope $end
$scope module or_c1 $end
$var wire 1 { a $end
$var wire 1 ) b $end
$var wire 1 > y $end
$upscope $end
$scope module or_c2 $end
$var wire 1 | a $end
$var wire 1 7 b $end
$var wire 1 3 c $end
$var wire 1 = y $end
$upscope $end
$scope module or_c3 $end
$var wire 1 } a $end
$var wire 1 6 b $end
$var wire 1 2 c $end
$var wire 1 / d $end
$var wire 1 < y $end
$upscope $end
$scope module or_c4 $end
$var wire 1 ~ a $end
$var wire 1 5 b $end
$var wire 1 1 c $end
$var wire 1 . d $end
$var wire 1 , e $end
$var wire 1 ; y $end
$upscope $end
$scope module or_cout $end
$var wire 1 !" a $end
$var wire 1 4 b $end
$var wire 1 0 c $end
$var wire 1 - d $end
$var wire 1 + e $end
$var wire 1 * f $end
$var wire 1 " y $end
$upscope $end
$scope module p0 $end
$var wire 1 "" a $end
$var wire 1 #" b $end
$var wire 1 $" y $end
$upscope $end
$scope module p1 $end
$var wire 1 %" a $end
$var wire 1 &" b $end
$var wire 1 '" y $end
$upscope $end
$scope module p2 $end
$var wire 1 (" a $end
$var wire 1 )" b $end
$var wire 1 *" y $end
$upscope $end
$scope module p3 $end
$var wire 1 +" a $end
$var wire 1 ," b $end
$var wire 1 -" y $end
$upscope $end
$scope module p4 $end
$var wire 1 ." a $end
$var wire 1 /" b $end
$var wire 1 0" y $end
$upscope $end
$scope module sum0 $end
$var wire 1 1" a $end
$var wire 1 % b $end
$var wire 1 2" y $end
$upscope $end
$scope module sum1 $end
$var wire 1 3" a $end
$var wire 1 > b $end
$var wire 1 4" y $end
$upscope $end
$scope module sum2 $end
$var wire 1 5" a $end
$var wire 1 = b $end
$var wire 1 6" y $end
$upscope $end
$scope module sum3 $end
$var wire 1 7" a $end
$var wire 1 < b $end
$var wire 1 8" y $end
$upscope $end
$scope module sum4 $end
$var wire 1 9" a $end
$var wire 1 ; b $end
$var wire 1 :" y $end
$upscope $end
$upscope $end
$upscope $end
$enddefinitions $end
$comment Show the parameter values. $end
$dumpall
$end
#0
$dumpvars
0:"
09"
08"
07"
06"
05"
04"
03"
12"
11"
00"
0/"
0."
0-"
0,"
0+"
0*"
0)"
0("
0'"
0&"
0%"
1$"
1#"
0""
0!"
0~
0}
0|
0{
0z
0y
0x
0w
0v
0u
0t
0s
0r
0q
0p
0o
0n
1m
0l
1k
1j
0i
0h
0g
0f
0e
0d
0c
0b
0a
1`
0_
0^
0]
0\
0[
0Z
0Y
0X
0W
0V
0U
1T
0S
0R
0Q
0P
0O
0N
0M
0L
0K
0J
0I
1H
0G
0F
0E
0D
0C
0B
0A
0@
0?
0>
0=
0<
0;
b0 :
b1 9
b1 8
07
06
05
04
03
02
01
00
0/
0.
0-
0,
0+
0*
0)
b1 (
b0 '
0&
0%
b1 $
b0 #
0"
b1 !
$end
#5000
1&
#10000
0&
#15000
1&
#20000
0&
#25000
1&
#30000
0&
#35000
b101 !
b101 8
16"
1=
1|
1B
1N
1\
b10 :
1q
1p
1&"
1o
1%"
b11 $
b11 (
b10 #
b10 '
1&
#40000
0&
#45000
1&
#50000
0&
#55000
1&
#60000
0&
#65000
1&
#70000
0&
#75000
18"
b1001 !
b1001 8
06"
1<
0=
0|
0B
0N
0\
1}
1D
1Q
0q
b100 :
1t
0p
1s
0&"
1)"
0o
1r
0%"
1("
b101 $
b101 (
b100 #
b100 '
1&
#80000
0&
#85000
1&
#90000
0&
#95000
1&
#100000
0&
#105000
1&
#110000
0&
#115000
1:"
b10001 !
b10001 8
08"
1;
0<
0}
0D
0Q
1~
1F
0t
b1000 :
1w
0s
1v
0)"
1,"
0r
1u
0("
1+"
b1001 $
b1001 (
b1000 #
b1000 '
1&
#120000
0&
#125000
1&
#130000
0&
#135000
1&
#140000
0&
#145000
1&
#150000
0&
#155000
b1 !
b1 8
0:"
1"
0;
0~
0F
1!"
0w
b10000 :
1z
0v
1y
0,"
1/"
0u
1x
0+"
1."
b10001 $
b10001 (
b10000 #
b10000 '
1&
#160000
0&
#165000
1&
#170000
0&
#175000
1&
#180000
0&
#185000
1&
#190000
0&
#195000
1;
16"
1=
1<
13
10
08"
0:"
15
0!"
1?
1G
1J
1S
1W
1_
1d
1i
13"
1C
1L
1U
1]
1P
1Z
1b
1g
17"
1E
1O
1Y
1a
1f
19"
1}
1D
1Q
04"
0z
1'"
1-"
b11011 9
10"
b100 :
1t
1>
0m
1p
1s
1v
0y
0#"
1&"
1)"
1,"
0/"
1l
1r
1""
1("
1)
b100 !
b100 8
02"
b1110 $
b1110 (
b10101 #
b10101 '
1%
1&
#200000
0&
#205000
1&
#210000
0&
#215000
1&
#220000
0&
#225000
1&
#230000
0&
#235000
1:"
0;
0"
18"
0<
05
00
0}
0D
0Q
1A
1I
1R
1M
1V
1^
1[
1c
1h
15"
16"
14"
b0 :
0t
b11111 9
1*"
0=
0>
1m
0s
0v
1#"
0)"
0,"
0l
1u
0""
1+"
03
0)
b11111 !
b11111 8
12"
b11 $
b11 (
b11100 #
b11100 '
0%
1&
#240000
0&
#245000
1&
#250000
0&
#255000
1&
#260000
0&
#265000
1&
#270000
0&
#275000
06"
08"
0:"
04"
1=
1<
1;
1"
1>
0m
0p
1v
1y
0#"
0&"
1,"
1/"
1l
1o
0u
0x
1""
1%"
0+"
0."
13
1/
1,
1*
1)
b0 !
b0 8
02"
b11000 $
b11000 (
b111 #
b111 '
1%
1&
